geos/__init__.py
geos/default_settings.py
geos/geometry.py
geos/kml.py
geos/mapsource.py
geos/print.py
geos/server.py
geos/mapsources/osm.xml
geos/scripts/__init__.py
geos/scripts/runserver.py
geos/static/custom.css
geos/static/custom.js
geos/static/empty_tile.png
geos/static/bootstrap/bootstrap-select.min.css
geos/static/bootstrap/bootstrap-select.min.js
geos/static/bootstrap/bootstrap.min.css
geos/static/bootstrap/bootstrap.min.js
geos/static/bootstrap/fonts/glyphicons-halflings-regular.eot
geos/static/bootstrap/fonts/glyphicons-halflings-regular.svg
geos/static/bootstrap/fonts/glyphicons-halflings-regular.ttf
geos/static/bootstrap/fonts/glyphicons-halflings-regular.woff
geos/static/bootstrap/fonts/glyphicons-halflings-regular.woff2
geos/static/jquery/LICENSE.txt
geos/static/jquery/jquery-1.10.2.min.js
geos/static/openlayer/LICENSE.md
geos/static/openlayer/ol.css
geos/static/openlayer/ol.js
geos/templates/index.html
geos/test/osm_mapnik_multilayer.xml
geos/test/mapsources/osm1.xml
geos/test/mapsources/osm10.xml
geos/test/mapsources/osm2.xml
geos/test/mapsources/osm3.xml
geos/test/mapsources/osm4.xml
geos/test/mapsources/osm5.xml
geos/test/mapsources/osm6.xml
geos/test/mapsources/osm7.xml
geos/test/mapsources/osm8.xml
geos/test/mapsources/osm9.xml
pykml_geos/__init__.py
pykml_geos/factory.py
pykml_geos/helpers.py
pykml_geos/parser.py
pykml_geos/util.py
pykml_geos/schemas/atom-author-link.xsd
pykml_geos/schemas/kml22gx.xsd
pykml_geos/schemas/ogckml22.xsd
pykml_geos/schemas/xAL.xsd
pykml_geos/test/test_factory.py
pykml_geos/test/test_helpers.py
pykml_geos/test/test_parser.py
pykml_geos/test/test_util.py
pykml_geos/test/testfiles/simple_file_with_comments.kml
pykml_geos/test/testfiles/google_kml_developers_guide/complete_tour_example.kml
pykml_geos/test/testfiles/google_kml_tutorial/using_the_cdata_element.kml
geos-0.2.3.dist-info/LICENSE
geos-0.2.3.dist-info/METADATA
geos-0.2.3.dist-info/WHEEL
geos-0.2.3.dist-info/entry_points.txt
geos-0.2.3.dist-info/top_level.txt
geos-0.2.3.dist-info/RECORD
